era_py/__init__.py
era_py/data.py
era_py/models.py
era_py/plots.py
era_py/tables.py
era_py-0.0.6.dist-info/METADATA
era_py-0.0.6.dist-info/WHEEL
era_py-0.0.6.dist-info/top_level.txt
era_py-0.0.6.dist-info/RECORD
